[
null,
{"id":1,"expanded":true,"name":"分类/功能模板","order":2,"parentId":3,"scrollX":1092,"scrollY":615.3333333333334},
{"id":2,"expanded":false,"name":"地图用模板","order":3,"parentId":3,"scrollX":1092,"scrollY":615.3333333333334},
{"id":3,"expanded":false,"name":"模板","order":1,"parentId":0,"scrollX":1092,"scrollY":615.3333333333334},
{"id":4,"expanded":true,"name":"功能","order":4,"parentId":0,"scrollX":819,"scrollY":461.5},
{"id":5,"expanded":true,"name":"地图","order":8,"parentId":0,"scrollX":819,"scrollY":461.5},
{"id":6,"expanded":false,"name":"界面","order":6,"parentId":0,"scrollX":819,"scrollY":461.5},
{"id":7,"expanded":true,"name":"测试 & 备份","order":75,"parentId":0,"scrollX":1092,"scrollY":615.3333333333334},
{"id":8,"expanded":false,"name":"L1 医院","order":9,"parentId":5,"scrollX":1092,"scrollY":615.3333333333334},
{"id":9,"expanded":true,"name":"001_医院大厅_中_备份","order":76,"parentId":7,"scrollX":1092,"scrollY":615.3333333333334},
{"id":10,"expanded":false,"name":"002_医院大厅_中_洗手间","order":25,"parentId":76,"scrollX":1092,"scrollY":624},
{"id":11,"expanded":false,"name":"004_医院大厅_左","order":10,"parentId":8,"scrollX":1092,"scrollY":615.3333333333334},
{"id":12,"expanded":true,"name":"003_医院大厅_中_值班室","order":26,"parentId":76,"scrollX":1082,"scrollY":764},
{"id":13,"expanded":true,"name":"封面","order":7,"parentId":6,"scrollX":1092,"scrollY":615.3333333333334},
{"id":14,"expanded":true,"name":"初始化","order":5,"parentId":4,"scrollX":1092,"scrollY":615.3333333333334},
{"id":15,"expanded":true,"name":"005_医院大厅_左_杂物间","order":11,"parentId":11,"scrollX":832,"scrollY":640},
{"id":16,"expanded":true,"name":"006_医院大厅_左_急诊室","order":12,"parentId":11,"scrollX":832,"scrollY":640},
{"id":17,"expanded":false,"name":"007_医院走廊_左","order":13,"parentId":8,"scrollX":1092,"scrollY":615.3333333333334},
{"id":18,"expanded":false,"name":"008_医院走廊_左_手术室走廊","order":14,"parentId":17,"scrollX":832,"scrollY":640},
{"id":19,"expanded":true,"name":"009_医院走廊_左_手术准备室","order":15,"parentId":17,"scrollX":832,"scrollY":640},
{"id":20,"expanded":false,"name":"010_医院走廊_左_手术室","order":16,"parentId":17,"scrollX":819,"scrollY":461.5},
{"id":21,"expanded":false,"name":"013_医院走廊_右","order":19,"parentId":8,"scrollX":819,"scrollY":461.5},
{"id":22,"expanded":false,"name":"012_医院走廊_中_停尸房","order":18,"parentId":23,"scrollX":832,"scrollY":640},
{"id":23,"expanded":false,"name":"011_医院走廊_中","order":17,"parentId":8,"scrollX":832,"scrollY":640},
{"id":24,"expanded":true,"name":"014_医院走廊_右_储物间","order":20,"parentId":21,"scrollX":832,"scrollY":640},
{"id":25,"expanded":false,"name":"015_医院大厅_右","order":21,"parentId":8,"scrollX":1092,"scrollY":615.3333333333334},
{"id":26,"expanded":false,"name":"016_医院大厅_右_紧急出口","order":22,"parentId":25,"scrollX":832,"scrollY":640},
{"id":27,"expanded":false,"name":"017_医院大厅_右_办公室","order":23,"parentId":25,"scrollX":832,"scrollY":640},
{"id":28,"expanded":false,"name":"L2 疗养所","order":27,"parentId":5,"scrollX":1092,"scrollY":615.3333333333334},
{"id":29,"expanded":true,"name":"018_疗养所大厅","order":28,"parentId":28,"scrollX":1092,"scrollY":615.3333333333334},
{"id":30,"expanded":true,"name":"020_疗养所走廊_左","order":30,"parentId":28,"scrollX":832,"scrollY":640},
{"id":31,"expanded":true,"name":"021_疗养所走廊_右","order":33,"parentId":28,"scrollX":819,"scrollY":461.5},
{"id":32,"expanded":false,"name":"019_疗养所办公室","order":29,"parentId":29,"scrollX":819,"scrollY":461.5},
{"id":33,"expanded":false,"name":"022_疗养所走廊_XRay","order":36,"parentId":28,"scrollX":819,"scrollY":461.5},
{"id":34,"expanded":false,"name":"023_疗养所走廊_左_病房1","order":31,"parentId":30,"scrollX":832,"scrollY":640},
{"id":35,"expanded":true,"name":"024_疗养所走廊_左_病房2","order":32,"parentId":30,"scrollX":832,"scrollY":640},
{"id":36,"expanded":false,"name":"025_疗养所走廊_右_尽头","order":34,"parentId":31,"scrollX":832,"scrollY":640},
{"id":37,"expanded":false,"name":"026_疗养所走廊_右_ICU病房","order":35,"parentId":31,"scrollX":832,"scrollY":640},
{"id":38,"expanded":false,"name":"B1 疯人院","order":47,"parentId":5,"scrollX":819,"scrollY":461.5},
{"id":39,"expanded":true,"name":"027_疯人院大厅","order":48,"parentId":38,"scrollX":819,"scrollY":461.5},
{"id":40,"expanded":true,"name":"029_疯人院走廊_上","order":50,"parentId":38,"scrollX":819,"scrollY":461.5},
{"id":41,"expanded":false,"name":"031_疯人院走廊_下","order":57,"parentId":38,"scrollX":819,"scrollY":461.5},
{"id":42,"expanded":false,"name":"028_疯人院大厅_解刨室1","order":49,"parentId":39,"scrollX":832,"scrollY":640},
{"id":43,"expanded":false,"name":"030_疯人院走廊_上_厕所","order":51,"parentId":40,"scrollX":832,"scrollY":640},
{"id":44,"expanded":true,"name":"032_疯人院走廊_上_尽头","order":52,"parentId":40,"scrollX":832,"scrollY":640},
{"id":45,"expanded":false,"name":"033_疯人院走廊_下_拐角","order":58,"parentId":41,"scrollX":832,"scrollY":640},
{"id":46,"expanded":false,"name":"035_疯人院走廊_上_尽头_监控室","order":53,"parentId":44,"scrollX":832,"scrollY":640},
{"id":47,"expanded":false,"name":"034_疯人院走廊_下_尽头","order":59,"parentId":45,"scrollX":832,"scrollY":640},
{"id":48,"expanded":true,"name":"036_疯人院走廊_上_尽头_监牢1","order":54,"parentId":44,"scrollX":832,"scrollY":640},
{"id":49,"expanded":true,"name":"037_疯人院走廊_上_尽头_监牢2","order":55,"parentId":44,"scrollX":832,"scrollY":640},
{"id":50,"expanded":true,"name":"038_疯人院走廊_上_尽头_监牢3","order":56,"parentId":44,"scrollX":832,"scrollY":640},
{"id":51,"expanded":true,"name":"039_疯人院走廊_下_拐角_解刨室2","order":60,"parentId":45,"scrollX":832,"scrollY":640},
{"id":52,"expanded":true,"name":"040_疯人院走廊_下_拐角_储物间","order":61,"parentId":45,"scrollX":832,"scrollY":640},
{"id":53,"expanded":true,"name":"041_疯人院走廊_下_拐角_停尸房","order":62,"parentId":45,"scrollX":832,"scrollY":640},
{"id":54,"expanded":false,"name":"L3 研究所","order":37,"parentId":5,"scrollX":819,"scrollY":461.5},
{"id":55,"expanded":true,"name":"B2 地下道","order":63,"parentId":5,"scrollX":819,"scrollY":461.5},
{"id":56,"expanded":false,"name":"042_研究所大厅_中","order":38,"parentId":54,"scrollX":819,"scrollY":461.5},
{"id":57,"expanded":false,"name":"044_研究所大厅_左","order":40,"parentId":54,"scrollX":832,"scrollY":640},
{"id":58,"expanded":false,"name":"043_研究所大厅_主实验室","order":39,"parentId":56,"scrollX":832,"scrollY":640},
{"id":59,"expanded":false,"name":"049_研究所大厅_右_尽头","order":45,"parentId":54,"scrollX":819,"scrollY":461.5},
{"id":60,"expanded":false,"name":"047_研究所大厅_右_拐角","order":43,"parentId":54,"scrollX":832,"scrollY":640},
{"id":61,"expanded":false,"name":"045_研究所大厅_机房","order":41,"parentId":57,"scrollX":832,"scrollY":640},
{"id":62,"expanded":true,"name":"046_研究所大厅_左_化验室","order":42,"parentId":57,"scrollX":832,"scrollY":640},
{"id":63,"expanded":false,"name":"048_研究所大厅_右_拐角_解刨室","order":44,"parentId":60,"scrollX":832,"scrollY":640},
{"id":64,"expanded":true,"name":"050_研究所大厅_右_转运间","order":46,"parentId":59,"scrollX":819,"scrollY":461.5},
{"id":65,"expanded":false,"name":"051_地下通道1","order":64,"parentId":55,"scrollX":819,"scrollY":461.5},
{"id":66,"expanded":false,"name":"052_地下角落1","order":65,"parentId":55,"scrollX":832,"scrollY":640},
{"id":67,"expanded":false,"name":"053_地下水道中心","order":68,"parentId":55,"scrollX":832,"scrollY":640},
{"id":68,"expanded":false,"name":"054_地下角落2","order":72,"parentId":55,"scrollX":832,"scrollY":640},
{"id":69,"expanded":false,"name":"052_地下角落1_无水","order":66,"parentId":66,"scrollX":832,"scrollY":640},
{"id":70,"expanded":true,"name":"053_地下水道中心_无水","order":69,"parentId":67,"scrollX":832,"scrollY":640},
{"id":71,"expanded":false,"name":"054_地下角落2_无水","order":73,"parentId":68,"scrollX":832,"scrollY":640},
{"id":72,"expanded":true,"name":"055_地下角落2_配电室","order":74,"parentId":68,"scrollX":832,"scrollY":640},
{"id":73,"expanded":true,"name":"056_地下角落1_维修通道","order":67,"parentId":66,"scrollX":832,"scrollY":640},
{"id":74,"expanded":true,"name":"057_地下水道中心_排污室","order":70,"parentId":67,"scrollX":832,"scrollY":640},
{"id":75,"expanded":true,"name":"058_地下水道中心_通往上层阶梯","order":71,"parentId":67,"scrollX":832,"scrollY":640},
{"id":76,"expanded":false,"name":"001_医院大厅_中","order":24,"parentId":8,"scrollX":1082.6666666666667,"scrollY":604.6666666666666},
{"id":77,"expanded":false,"name":"002_医院大厅_中_洗手间_备份","order":77,"parentId":9,"scrollX":832,"scrollY":640},
{"id":78,"expanded":true,"name":"003_医院大厅_中_值班室_备份","order":78,"parentId":9,"scrollX":832,"scrollY":640}
]